pysmore/__init__.py
pysmore/pysmore.py
pysmore-0.0.1.dist-info/LICENSE
pysmore-0.0.1.dist-info/WHEEL
pysmore-0.0.1.dist-info/METADATA
pysmore-0.0.1.dist-info/RECORD
