Metadata-Version: 2.1
Name: pysmore
Version: 0.0.1
Summary: Python version of SMORe: Modularize Graph Embedding for Recommendation
Home-page: https://github.com/josix/pysmore
License: MIT
Author: Josix Wang
Author-email: josixwang@gmail.com
Requires-Python: >=3.9,<4.0
Classifier: License :: OSI Approved :: MIT License
Classifier: Programming Language :: Python :: 3
Classifier: Programming Language :: Python :: 3.10
Classifier: Programming Language :: Python :: 3.9
Project-URL: Repository, https://github.com/josix/pysmore
